defuss_apl/__init__.py
defuss_apl/cli.py
defuss_apl/parser.py
defuss_apl/providers.py
defuss_apl/py.typed
defuss_apl/runtime.py
defuss_apl/test_utils.py
defuss_apl/tools.py
defuss_apl-1.1.0.dist-info/METADATA
defuss_apl-1.1.0.dist-info/WHEEL
defuss_apl-1.1.0.dist-info/entry_points.txt
defuss_apl-1.1.0.dist-info/top_level.txt
defuss_apl-1.1.0.dist-info/RECORD
