Metadata-Version: 2.4
Name: defuss-apl
Version: 1.1.0
Summary: Agentic Prompting Language (APL) - Python Implementation
Author: Defuss Team
License: MIT
Project-URL: Homepage, https://github.com/defuss/defuss
Project-URL: Documentation, https://github.com/defuss/defuss/tree/main/packages/apl
Project-URL: Repository, https://github.com/defuss/defuss.git
Project-URL: Issues, https://github.com/defuss/defuss/issues
Keywords: apl,agentic,prompting,language,llm,ai,jinja,workflow
Classifier: Development Status :: 4 - Beta
Classifier: Intended Audience :: Developers
Classifier: License :: OSI Approved :: MIT License
Classifier: Programming Language :: Python :: 3
Classifier: Programming Language :: Python :: 3.8
Classifier: Programming Language :: Python :: 3.9
Classifier: Programming Language :: Python :: 3.10
Classifier: Programming Language :: Python :: 3.11
Classifier: Programming Language :: Python :: 3.12
Classifier: Programming Language :: Python :: 3.13
Classifier: Topic :: Software Development :: Libraries :: Python Modules
Classifier: Topic :: Scientific/Engineering :: Artificial Intelligence
Requires-Python: >=3.8
Requires-Dist: jinja2>=3.0.0
Provides-Extra: openai
Requires-Dist: openai>=1.0.0; extra == "openai"
Provides-Extra: dev
Requires-Dist: pytest>=7.0.0; extra == "dev"
Requires-Dist: pytest-asyncio>=0.21.0; extra == "dev"
Requires-Dist: black>=22.0.0; extra == "dev"
Requires-Dist: flake8>=5.0.0; extra == "dev"
Requires-Dist: mypy>=1.0.0; extra == "dev"
Provides-Extra: all
Requires-Dist: openai>=1.0.0; extra == "all"
